{"_id": "0305-723", "pgId": "0305", "numCols": 7, "numDataRows": 17, "pgTitle": "England national rugby union team \u2013 Results 2000\u2013present", "tableCaption": "", "numNumericCols": 2, "headers": [{"text": "Opposing Teams", "isNumeric": false, "links": []}, {"text": "For", "isNumeric": false, "links": []}, {"text": "Against", "isNumeric": false, "links": []}, {"text": "Date", "isNumeric": false, "links": []}, {"text": "Venue", "isNumeric": false, "links": []}, {"text": "Competition", "isNumeric": false, "links": []}, {"text": "Winner", "isNumeric": false, "links": []}], "rows": [[{"text": "", "isNumeric": false, "links": []}, {"text": "42", "isNumeric": false, "links": []}, {"text": "20", "isNumeric": false, "links": []}, {"text": "03/02/2007", "isNumeric": false, "links": []}, {"text": "Twickenham", "isNumeric": false, "links": ["http://www.wikipedia.org/wiki/Twickenham_Stadium"]}, {"text": "Six Nations", "isNumeric": false, "links": ["http://www.wikipedia.org/wiki/2007_Six_Nations_Championship"]}, {"text": "", "isNumeric": false, "links": []}], [{"text": "Italy", "isNumeric": false, "links": ["http://www.wikipedia.org/wiki/Italy_national_rugby_union_team"]}, {"text": "20", "isNumeric": false, "links": []}, {"text": "7", "isNumeric": false, "links": []}, {"text": "10/02/2007", "isNumeric": false, "links": []}, {"text": "Twickenham", "isNumeric": false, "links": ["http://www.wikipedia.org/wiki/Twickenham_Stadium"]}, {"text": "Six Nations", "isNumeric": false, "links": ["http://www.wikipedia.org/wiki/2007_Six_Nations_Championship"]}, {"text": "", "isNumeric": false, "links": []}], [{"text": "Ireland", "isNumeric": false, "links": ["http://www.wikipedia.org/wiki/Ireland_national_rugby_union_team"]}, {"text": "13", "isNumeric": false, "links": []}, {"text": "43", "isNumeric": false, "links": []}, {"text": "24/02/2007", "isNumeric": false, "links": []}, {"text": "Croke Park", "isNumeric": false, "links": ["http://www.wikipedia.org/wiki/Croke_Park"]}, {"text": "Six Nations", "isNumeric": false, "links": ["http://www.wikipedia.org/wiki/2007_Six_Nations_Championship"]}, {"text": "Ireland", "isNumeric": false, "links": ["http://www.wikipedia.org/wiki/Irish_Rugby_Football_Union"]}], [{"text": "", "isNumeric": false, "links": []}, {"text": "26", "isNumeric": false, "links": []}, {"text": "18", "isNumeric": false, "links": []}, {"text": "11/03/2007", "isNumeric": false, "links": []}, {"text": "Twickenham", "isNumeric": false, "links": ["http://www.wikipedia.org/wiki/Twickenham_Stadium"]}, {"text": "Six Nations", "isNumeric": false, "links": ["http://www.wikipedia.org/wiki/2007_Six_Nations_Championship"]}, {"text": "", "isNumeric": false, "links": []}], [{"text": "", "isNumeric": false, "links": []}, {"text": "18", "isNumeric": false, "links": []}, {"text": "27", "isNumeric": false, "links": []}, {"text": "17/03/2007", "isNumeric": false, "links": []}, {"text": "Millennium Stadium", "isNumeric": false, "links": ["http://www.wikipedia.org/wiki/Millennium_Stadium"]}, {"text": "Six Nations", "isNumeric": false, "links": ["http://www.wikipedia.org/wiki/2007_Six_Nations_Championship"]}, {"text": "", "isNumeric": false, "links": []}], [{"text": "", "isNumeric": false, "links": []}, {"text": "10", "isNumeric": false, "links": []}, {"text": "58", "isNumeric": false, "links": []}, {"text": "26/05/2007", "isNumeric": false, "links": []}, {"text": "Vodacom Park", "isNumeric": false, "links": ["http://www.wikipedia.org/wiki/Free_State_Stadium"]}, {"text": "Summer Tour", "isNumeric": false, "links": ["http://www.wikipedia.org/wiki/2007_mid-year_rugby_union_internationals"]}, {"text": "", "isNumeric": false, "links": []}], [{"text": "", "isNumeric": false, "links": []}, {"text": "22", "isNumeric": false, "links": []}, {"text": "55", "isNumeric": false, "links": []}, {"text": "02/06/2007", "isNumeric": false, "links": []}, {"text": "Loftus Versfeld", "isNumeric": false, "links": ["http://www.wikipedia.org/wiki/Loftus_Versfeld_Stadium"]}, {"text": "Summer Tour", "isNumeric": false, "links": ["http://www.wikipedia.org/wiki/2007_mid-year_rugby_union_internationals"]}, {"text": "", "isNumeric": false, "links": []}], [{"text": "", "isNumeric": false, "links": []}, {"text": "62", "isNumeric": false, "links": []}, {"text": "5", "isNumeric": false, "links": []}, {"text": "04/08/2007", "isNumeric": false, "links": []}, {"text": "Twickenham", "isNumeric": false, "links": ["http://www.wikipedia.org/wiki/Twickenham_Stadium"]}, {"text": "Rugby World Cup Warm-Up Test", "isNumeric": false, "links": ["http://www.wikipedia.org/wiki/2007_Rugby_World_Cup_warm-up_matches"]}, {"text": "", "isNumeric": false, "links": []}], [{"text": "", "isNumeric": false, "links": []}, {"text": "15", "isNumeric": false, "links": []}, {"text": "21", "isNumeric": false, "links": []}, {"text": "11/08/2007", "isNumeric": false, "links": []}, {"text": "Twickenham", "isNumeric": false, "links": ["http://www.wikipedia.org/wiki/Twickenham_Stadium"]}, {"text": "Rugby World Cup Warm-Up Test", "isNumeric": false, "links": ["http://www.wikipedia.org/wiki/2007_Rugby_World_Cup_warm-up_matches"]}, {"text": "", "isNumeric": false, "links": []}], [{"text": "", "isNumeric": false, "links": []}, {"text": "9", "isNumeric": false, "links": []}, {"text": "22", "isNumeric": false, "links": []}, {"text": "18/08/2007", "isNumeric": false, "links": []}, {"text": "Stade V\u00e9lodrome", "isNumeric": false, "links": ["http://www.wikipedia.org/wiki/Stade_V\u00e9lodrome"]}, {"text": "Rugby World Cup Warm-Up Test", "isNumeric": false, "links": ["http://www.wikipedia.org/wiki/2007_Rugby_World_Cup_warm-up_matches"]}, {"text": "", "isNumeric": false, "links": []}], [{"text": "U.S.A.", "isNumeric": false, "links": ["http://www.wikipedia.org/wiki/United_States_national_rugby_union_team"]}, {"text": "28", "isNumeric": false, "links": []}, {"text": "10", "isNumeric": false, "links": []}, {"text": "08/09/2007", "isNumeric": false, "links": []}, {"text": "Stade F\u00e9lix-Bollaert", "isNumeric": false, "links": ["http://www.wikipedia.org/wiki/Stade_Bollaert-Delelis"]}, {"text": "World Cup Pool 1", "isNumeric": false, "links": ["http://www.wikipedia.org/wiki/2007_Rugby_World_Cup"]}, {"text": "", "isNumeric": false, "links": []}], [{"text": "", "isNumeric": false, "links": []}, {"text": "0", "isNumeric": false, "links": []}, {"text": "36", "isNumeric": false, "links": []}, {"text": "14/09/2007", "isNumeric": false, "links": []}, {"text": "Stade de France", "isNumeric": false, "links": ["http://www.wikipedia.org/wiki/Stade_de_France"]}, {"text": "World Cup Pool 1", "isNumeric": false, "links": ["http://www.wikipedia.org/wiki/2007_Rugby_World_Cup"]}, {"text": "", "isNumeric": false, "links": []}], [{"text": "Samoa", "isNumeric": false, "links": ["http://www.wikipedia.org/wiki/Samoa_national_rugby_union_team"]}, {"text": "44", "isNumeric": false, "links": []}, {"text": "22", "isNumeric": false, "links": []}, {"text": "22/09/2007", "isNumeric": false, "links": []}, {"text": "Stade de la Beaujoire", "isNumeric": false, "links": ["http://www.wikipedia.org/wiki/Stade_de_la_Beaujoire"]}, {"text": "World Cup Pool 1", "isNumeric": false, "links": ["http://www.wikipedia.org/wiki/2007_Rugby_World_Cup"]}, {"text": "", "isNumeric": false, "links": []}], [{"text": "", "isNumeric": false, "links": []}, {"text": "36", "isNumeric": false, "links": []}, {"text": "20", "isNumeric": false, "links": []}, {"text": "28/09/2007", "isNumeric": false, "links": []}, {"text": "Parc des Princes", "isNumeric": false, "links": ["http://www.wikipedia.org/wiki/Parc_des_Princes"]}, {"text": "World Cup Pool 1", "isNumeric": false, "links": ["http://www.wikipedia.org/wiki/2007_Rugby_World_Cup"]}, {"text": "", "isNumeric": false, "links": []}], [{"text": "Australia", "isNumeric": false, "links": ["http://www.wikipedia.org/wiki/Australia_national_rugby_union_team"]}, {"text": "12", "isNumeric": false, "links": []}, {"text": "10", "isNumeric": false, "links": []}, {"text": "06/10/2007", "isNumeric": false, "links": []}, {"text": "Stade V\u00e9lodrome", "isNumeric": false, "links": ["http://www.wikipedia.org/wiki/Stade_V\u00e9lodrome"]}, {"text": "World Cup Quarter Final", "isNumeric": false, "links": ["http://www.wikipedia.org/wiki/2007_Rugby_World_Cup"]}, {"text": "", "isNumeric": false, "links": []}], [{"text": "", "isNumeric": false, "links": []}, {"text": "14", "isNumeric": false, "links": []}, {"text": "9", "isNumeric": false, "links": []}, {"text": "13/10/2007", "isNumeric": false, "links": []}, {"text": "Stade de France", "isNumeric": false, "links": ["http://www.wikipedia.org/wiki/Stade_de_France"]}, {"text": "World Cup Semi Final", "isNumeric": false, "links": ["http://www.wikipedia.org/wiki/2007_Rugby_World_Cup"]}, {"text": "", "isNumeric": false, "links": []}], [{"text": "", "isNumeric": false, "links": []}, {"text": "6", "isNumeric": false, "links": []}, {"text": "15", "isNumeric": false, "links": []}, {"text": "20/10/2007", "isNumeric": false, "links": []}, {"text": "Stade de France", "isNumeric": false, "links": ["http://www.wikipedia.org/wiki/Stade_de_France"]}, {"text": "World Cup Final", "isNumeric": false, "links": ["http://www.wikipedia.org/wiki/2007_Rugby_World_Cup_Final"]}, {"text": "", "isNumeric": false, "links": []}]]}