{"_id": "0239-921", "pgId": "0239", "numCols": 4, "numDataRows": 100, "pgTitle": "Triple J Hottest 100, 2007", "tableCaption": "", "numNumericCols": 1, "headers": [{"text": "#", "isNumeric": false, "links": []}, {"text": "Song", "isNumeric": false, "links": []}, {"text": "Artist", "isNumeric": false, "links": []}, {"text": "Country of Origin", "isNumeric": false, "links": []}], "rows": [[{"text": "1", "isNumeric": false, "links": []}, {"text": "Knights of Cydonia", "isNumeric": false, "links": ["http://www.wikipedia.org/wiki/Knights_of_Cydonia"]}, {"text": "Muse", "isNumeric": false, "links": ["http://www.wikipedia.org/wiki/Muse_(band)"]}, {"text": "United Kingdom", "isNumeric": false, "links": ["http://www.wikipedia.org/wiki/United_Kingdom"]}], [{"text": "2", "isNumeric": false, "links": []}, {"text": "Straight Lines", "isNumeric": false, "links": ["http://www.wikipedia.org/wiki/Straight_Lines_(song)"]}, {"text": "Silverchair", "isNumeric": false, "links": ["http://www.wikipedia.org/wiki/Silverchair"]}, {"text": "Australia", "isNumeric": false, "links": ["http://www.wikipedia.org/wiki/Australia"]}], [{"text": "3", "isNumeric": false, "links": []}, {"text": "On Call", "isNumeric": false, "links": ["http://www.wikipedia.org/wiki/On_Call"]}, {"text": "Kings of Leon", "isNumeric": false, "links": ["http://www.wikipedia.org/wiki/Kings_of_Leon"]}, {"text": "United States", "isNumeric": false, "links": ["http://www.wikipedia.org/wiki/United_States"]}], [{"text": "4", "isNumeric": false, "links": []}, {"text": "Better Than", "isNumeric": false, "links": ["http://www.wikipedia.org/wiki/Better_Than"]}, {"text": "The John Butler Trio", "isNumeric": false, "links": ["http://www.wikipedia.org/wiki/John_Butler_Trio"]}, {"text": "Australia", "isNumeric": false, "links": []}], [{"text": "5", "isNumeric": false, "links": []}, {"text": "This Heart Attack", "isNumeric": false, "links": ["http://www.wikipedia.org/wiki/This_Heart_Attack"]}, {"text": "Faker", "isNumeric": false, "links": ["http://www.wikipedia.org/wiki/Faker_(band)"]}, {"text": "Australia", "isNumeric": false, "links": []}], [{"text": "6", "isNumeric": false, "links": []}, {"text": "The Pretender", "isNumeric": false, "links": ["http://www.wikipedia.org/wiki/The_Pretender_(Foo_Fighters_song)"]}, {"text": "Foo Fighters", "isNumeric": false, "links": ["http://www.wikipedia.org/wiki/Foo_Fighters"]}, {"text": "United States", "isNumeric": false, "links": []}], [{"text": "7", "isNumeric": false, "links": []}, {"text": "Harder, Better, Faster, Stronger", "isNumeric": false, "links": ["http://www.wikipedia.org/wiki/Harder,_Better,_Faster,_Stronger"]}, {"text": "Daft Punk", "isNumeric": false, "links": ["http://www.wikipedia.org/wiki/Daft_Punk"]}, {"text": "France", "isNumeric": false, "links": ["http://www.wikipedia.org/wiki/France"]}], [{"text": "8", "isNumeric": false, "links": []}, {"text": "Hang Me Up to Dry", "isNumeric": false, "links": ["http://www.wikipedia.org/wiki/Hang_Me_Up_to_Dry"]}, {"text": "Cold War Kids", "isNumeric": false, "links": ["http://www.wikipedia.org/wiki/Cold_War_Kids"]}, {"text": "United States", "isNumeric": false, "links": []}], [{"text": "9", "isNumeric": false, "links": []}, {"text": "I'll Kill Her", "isNumeric": false, "links": []}, {"text": "Soko", "isNumeric": false, "links": ["http://www.wikipedia.org/wiki/Soko_(singer)"]}, {"text": "France", "isNumeric": false, "links": []}], [{"text": "10", "isNumeric": false, "links": []}, {"text": "Don't Fight It", "isNumeric": false, "links": []}, {"text": "The Panics", "isNumeric": false, "links": ["http://www.wikipedia.org/wiki/The_Panics"]}, {"text": "Australia", "isNumeric": false, "links": []}], [{"text": "11", "isNumeric": false, "links": []}, {"text": "Vitriol", "isNumeric": false, "links": []}, {"text": "Bluejuice", "isNumeric": false, "links": ["http://www.wikipedia.org/wiki/Bluejuice"]}, {"text": "Australia", "isNumeric": false, "links": []}], [{"text": "12", "isNumeric": false, "links": []}, {"text": "Let's Dance to Joy Division", "isNumeric": false, "links": ["http://www.wikipedia.org/wiki/Let's_Dance_to_Joy_Division"]}, {"text": "The Wombats", "isNumeric": false, "links": ["http://www.wikipedia.org/wiki/The_Wombats"]}, {"text": "United Kingdom", "isNumeric": false, "links": []}], [{"text": "13", "isNumeric": false, "links": []}, {"text": "Ruby", "isNumeric": false, "links": ["http://www.wikipedia.org/wiki/Ruby_(song)"]}, {"text": "Kaiser Chiefs", "isNumeric": false, "links": ["http://www.wikipedia.org/wiki/Kaiser_Chiefs"]}, {"text": "United Kingdom", "isNumeric": false, "links": []}], [{"text": "14", "isNumeric": false, "links": []}, {"text": "Ice Cream", "isNumeric": false, "links": []}, {"text": "Muscles", "isNumeric": false, "links": ["http://www.wikipedia.org/wiki/Muscles_(musician)"]}, {"text": "Australia", "isNumeric": false, "links": []}], [{"text": "15", "isNumeric": false, "links": []}, {"text": "Lost and Running", "isNumeric": false, "links": ["http://www.wikipedia.org/wiki/Lost_and_Running"]}, {"text": "Powderfinger", "isNumeric": false, "links": ["http://www.wikipedia.org/wiki/Powderfinger"]}, {"text": "Australia", "isNumeric": false, "links": []}], [{"text": "16", "isNumeric": false, "links": []}, {"text": "Snakeskin", "isNumeric": false, "links": ["http://www.wikipedia.org/wiki/Snakeskin_(song)"]}, {"text": "Gyroscope", "isNumeric": false, "links": ["http://www.wikipedia.org/wiki/Gyroscope_(band)"]}, {"text": "Australia", "isNumeric": false, "links": []}], [{"text": "17", "isNumeric": false, "links": []}, {"text": "Paper Planes", "isNumeric": false, "links": ["http://www.wikipedia.org/wiki/Paper_Planes"]}, {"text": "M.I.A", "isNumeric": false, "links": ["http://www.wikipedia.org/wiki/M.I.A._(rapper)"]}, {"text": "United Kingdom", "isNumeric": false, "links": []}], [{"text": "18", "isNumeric": false, "links": []}, {"text": "My People", "isNumeric": false, "links": ["http://www.wikipedia.org/wiki/My_People_(The_Presets_song)"]}, {"text": "The Presets", "isNumeric": false, "links": ["http://www.wikipedia.org/wiki/The_Presets"]}, {"text": "Australia", "isNumeric": false, "links": []}], [{"text": "19", "isNumeric": false, "links": []}, {"text": "Heart It Races", "isNumeric": false, "links": []}, {"text": "Architecture in Helsinki", "isNumeric": false, "links": ["http://www.wikipedia.org/wiki/Architecture_in_Helsinki"]}, {"text": "Australia", "isNumeric": false, "links": []}], [{"text": "20", "isNumeric": false, "links": []}, {"text": "Stronger", "isNumeric": false, "links": ["http://www.wikipedia.org/wiki/Stronger_(Kanye_West_song)"]}, {"text": "Kanye West", "isNumeric": false, "links": ["http://www.wikipedia.org/wiki/Kanye_West"]}, {"text": "United States", "isNumeric": false, "links": []}], [{"text": "21", "isNumeric": false, "links": []}, {"text": "The Salmon Dance", "isNumeric": false, "links": ["http://www.wikipedia.org/wiki/The_Salmon_Dance"]}, {"text": "The Chemical Brothers", "isNumeric": false, "links": ["http://www.wikipedia.org/wiki/The_Chemical_Brothers"]}, {"text": "United Kingdom", "isNumeric": false, "links": []}], [{"text": "22", "isNumeric": false, "links": []}, {"text": "Used To Get High", "isNumeric": false, "links": []}, {"text": "The John Butler Trio", "isNumeric": false, "links": []}, {"text": "Australia", "isNumeric": false, "links": []}], [{"text": "23", "isNumeric": false, "links": []}, {"text": "Icky Thump", "isNumeric": false, "links": ["http://www.wikipedia.org/wiki/Icky_Thump_(song)"]}, {"text": "The White Stripes", "isNumeric": false, "links": ["http://www.wikipedia.org/wiki/The_White_Stripes"]}, {"text": "United States", "isNumeric": false, "links": []}], [{"text": "24", "isNumeric": false, "links": []}, {"text": "Hunting For Witches", "isNumeric": false, "links": ["http://www.wikipedia.org/wiki/Hunting_for_Witches"]}, {"text": "Bloc Party", "isNumeric": false, "links": ["http://www.wikipedia.org/wiki/Bloc_Party"]}, {"text": "United Kingdom", "isNumeric": false, "links": []}], [{"text": "25", "isNumeric": false, "links": []}, {"text": "We Get Around", "isNumeric": false, "links": []}, {"text": "Urthboy", "isNumeric": false, "links": ["http://www.wikipedia.org/wiki/Urthboy"]}, {"text": "Australia", "isNumeric": false, "links": []}], [{"text": "26", "isNumeric": false, "links": []}, {"text": "Recapturing The Vibe (Restrung)", "isNumeric": false, "links": []}, {"text": "Hilltop Hoods", "isNumeric": false, "links": ["http://www.wikipedia.org/wiki/Hilltop_Hoods"]}, {"text": "Australia", "isNumeric": false, "links": []}], [{"text": "27", "isNumeric": false, "links": []}, {"text": "Just a Song About Ping Pong", "isNumeric": false, "links": ["http://www.wikipedia.org/wiki/Just_a_Song_About_Ping_Pong"]}, {"text": "Operator Please", "isNumeric": false, "links": ["http://www.wikipedia.org/wiki/Operator_Please"]}, {"text": "Australia", "isNumeric": false, "links": []}], [{"text": "28", "isNumeric": false, "links": []}, {"text": "Lazy Eye", "isNumeric": false, "links": ["http://www.wikipedia.org/wiki/Lazy_Eye_(Silversun_Pickups_song)"]}, {"text": "Silversun Pickups", "isNumeric": false, "links": ["http://www.wikipedia.org/wiki/Silversun_Pickups"]}, {"text": "United States", "isNumeric": false, "links": []}], [{"text": "29", "isNumeric": false, "links": []}, {"text": "Real Love", "isNumeric": false, "links": ["http://www.wikipedia.org/wiki/Real_Love_(Beatles_song)"]}, {"text": "Regina Spektor", "isNumeric": false, "links": ["http://www.wikipedia.org/wiki/Regina_Spektor"]}, {"text": "United States", "isNumeric": false, "links": []}], [{"text": "30", "isNumeric": false, "links": []}, {"text": "If You Keep Losing Sleep", "isNumeric": false, "links": ["http://www.wikipedia.org/wiki/If_You_Keep_Losing_Sleep"]}, {"text": "Silverchair", "isNumeric": false, "links": []}, {"text": "Australia", "isNumeric": false, "links": []}], [{"text": "31", "isNumeric": false, "links": []}, {"text": "Wasted", "isNumeric": false, "links": []}, {"text": "Angus and Julia Stone", "isNumeric": false, "links": ["http://www.wikipedia.org/wiki/Angus_&_Julia_Stone"]}, {"text": "Australia", "isNumeric": false, "links": []}], [{"text": "32", "isNumeric": false, "links": []}, {"text": "Opinions Won't Keep You Warm at Night", "isNumeric": false, "links": ["http://www.wikipedia.org/wiki/Opinions_Won't_Keep_You_Warm_at_Night"]}, {"text": "Kisschasy", "isNumeric": false, "links": ["http://www.wikipedia.org/wiki/Kisschasy"]}, {"text": "Australia", "isNumeric": false, "links": []}], [{"text": "33", "isNumeric": false, "links": []}, {"text": "Fans", "isNumeric": false, "links": ["http://www.wikipedia.org/wiki/Fans_(song)"]}, {"text": "Kings of Leon", "isNumeric": false, "links": []}, {"text": "United States", "isNumeric": false, "links": []}], [{"text": "34", "isNumeric": false, "links": []}, {"text": "1234", "isNumeric": false, "links": ["http://www.wikipedia.org/wiki/1234_(Feist_song)"]}, {"text": "Feist", "isNumeric": false, "links": ["http://www.wikipedia.org/wiki/Feist_(singer)"]}, {"text": "Canada", "isNumeric": false, "links": ["http://www.wikipedia.org/wiki/Canada"]}], [{"text": "35", "isNumeric": false, "links": []}, {"text": "D.A.N.C.E.", "isNumeric": false, "links": ["http://www.wikipedia.org/wiki/D.A.N.C.E."]}, {"text": "Justice", "isNumeric": false, "links": ["http://www.wikipedia.org/wiki/Justice_(band)"]}, {"text": "France", "isNumeric": false, "links": []}], [{"text": "36", "isNumeric": false, "links": []}, {"text": "Hold Music", "isNumeric": false, "links": []}, {"text": "Architecture in Helsinki", "isNumeric": false, "links": []}, {"text": "Australia", "isNumeric": false, "links": []}], [{"text": "37", "isNumeric": false, "links": []}, {"text": "Hospital Beds", "isNumeric": false, "links": []}, {"text": "Cold War Kids", "isNumeric": false, "links": []}, {"text": "United States", "isNumeric": false, "links": []}], [{"text": "38", "isNumeric": false, "links": []}, {"text": "I Thought About You", "isNumeric": false, "links": []}, {"text": "The Beautiful Girls", "isNumeric": false, "links": ["http://www.wikipedia.org/wiki/The_Beautiful_Girls"]}, {"text": "Australia", "isNumeric": false, "links": []}], [{"text": "39", "isNumeric": false, "links": []}, {"text": "Hearts on Fire", "isNumeric": false, "links": ["http://www.wikipedia.org/wiki/Hearts_on_Fire_(Cut_Copy_song)"]}, {"text": "Cut Copy", "isNumeric": false, "links": ["http://www.wikipedia.org/wiki/Cut_Copy"]}, {"text": "Australia", "isNumeric": false, "links": []}], [{"text": "40", "isNumeric": false, "links": []}, {"text": "I Still Remember", "isNumeric": false, "links": ["http://www.wikipedia.org/wiki/I_Still_Remember"]}, {"text": "Bloc Party", "isNumeric": false, "links": []}, {"text": "United Kingdom", "isNumeric": false, "links": []}], [{"text": "41", "isNumeric": false, "links": []}, {"text": "Dashboard", "isNumeric": false, "links": ["http://www.wikipedia.org/wiki/Dashboard_(song)"]}, {"text": "Modest Mouse", "isNumeric": false, "links": ["http://www.wikipedia.org/wiki/Modest_Mouse"]}, {"text": "United States", "isNumeric": false, "links": []}], [{"text": "42", "isNumeric": false, "links": []}, {"text": "Back In Your Head", "isNumeric": false, "links": ["http://www.wikipedia.org/wiki/The_Con_(album)"]}, {"text": "Tegan and Sara", "isNumeric": false, "links": ["http://www.wikipedia.org/wiki/Tegan_and_Sara"]}, {"text": "Canada", "isNumeric": false, "links": []}], [{"text": "43", "isNumeric": false, "links": []}, {"text": "Superstar", "isNumeric": false, "links": ["http://www.wikipedia.org/wiki/Superstar_(Lupe_Fiasco_song)"]}, {"text": "Lupe Fiasco", "isNumeric": false, "links": ["http://www.wikipedia.org/wiki/Lupe_Fiasco"]}, {"text": "United States", "isNumeric": false, "links": []}], [{"text": "44", "isNumeric": false, "links": []}, {"text": "Teenagers", "isNumeric": false, "links": ["http://www.wikipedia.org/wiki/Teenagers_(song)"]}, {"text": "My Chemical Romance", "isNumeric": false, "links": ["http://www.wikipedia.org/wiki/My_Chemical_Romance"]}, {"text": "United States", "isNumeric": false, "links": []}], [{"text": "45", "isNumeric": false, "links": []}, {"text": "The Beast", "isNumeric": false, "links": ["http://www.wikipedia.org/wiki/The_Beast_(Angus_and_Julia_Stone_album)"]}, {"text": "Angus and Julia Stone", "isNumeric": false, "links": []}, {"text": "Australia", "isNumeric": false, "links": []}], [{"text": "46", "isNumeric": false, "links": []}, {"text": "Tie Up My Hands", "isNumeric": false, "links": ["http://www.wikipedia.org/wiki/Tie_Up_My_Hands"]}, {"text": "British India", "isNumeric": false, "links": ["http://www.wikipedia.org/wiki/British_India_(band)"]}, {"text": "Australia", "isNumeric": false, "links": []}], [{"text": "47", "isNumeric": false, "links": []}, {"text": "What If", "isNumeric": false, "links": []}, {"text": "Cog", "isNumeric": false, "links": ["http://www.wikipedia.org/wiki/Cog_(band)"]}, {"text": "Australia", "isNumeric": false, "links": []}], [{"text": "48", "isNumeric": false, "links": []}, {"text": "Flux", "isNumeric": false, "links": ["http://www.wikipedia.org/wiki/Flux_(song)"]}, {"text": "Bloc Party", "isNumeric": false, "links": []}, {"text": "United Kingdom", "isNumeric": false, "links": []}], [{"text": "49", "isNumeric": false, "links": []}, {"text": "Fluorescent Adolescent", "isNumeric": false, "links": ["http://www.wikipedia.org/wiki/Fluorescent_Adolescent"]}, {"text": "Arctic Monkeys", "isNumeric": false, "links": ["http://www.wikipedia.org/wiki/Arctic_Monkeys"]}, {"text": "United Kingdom", "isNumeric": false, "links": []}], [{"text": "50", "isNumeric": false, "links": []}, {"text": "So Many Nights", "isNumeric": false, "links": ["http://www.wikipedia.org/wiki/So_Many_Nights_(song)"]}, {"text": "The Cat Empire", "isNumeric": false, "links": ["http://www.wikipedia.org/wiki/The_Cat_Empire"]}, {"text": "Australia", "isNumeric": false, "links": []}], [{"text": "51", "isNumeric": false, "links": []}, {"text": "Peachy", "isNumeric": false, "links": ["http://www.wikipedia.org/wiki/Peachy"]}, {"text": "Missy Higgins", "isNumeric": false, "links": ["http://www.wikipedia.org/wiki/Missy_Higgins"]}, {"text": "Australia", "isNumeric": false, "links": []}], [{"text": "52", "isNumeric": false, "links": []}, {"text": "Spray on Pants", "isNumeric": false, "links": ["http://www.wikipedia.org/wiki/Spray_on_Pants"]}, {"text": "Kisschasy", "isNumeric": false, "links": []}, {"text": "Australia", "isNumeric": false, "links": []}], [{"text": "53", "isNumeric": false, "links": []}, {"text": "Steer", "isNumeric": false, "links": ["http://www.wikipedia.org/wiki/Steer_(song)"]}, {"text": "Missy Higgins", "isNumeric": false, "links": []}, {"text": "Australia", "isNumeric": false, "links": []}], [{"text": "54", "isNumeric": false, "links": []}, {"text": "Golden Skans", "isNumeric": false, "links": ["http://www.wikipedia.org/wiki/Golden_Skans"]}, {"text": "Klaxons", "isNumeric": false, "links": ["http://www.wikipedia.org/wiki/Klaxons"]}, {"text": "United Kingdom", "isNumeric": false, "links": []}], [{"text": "55", "isNumeric": false, "links": []}, {"text": "Good Excuse", "isNumeric": false, "links": []}, {"text": "The John Butler Trio", "isNumeric": false, "links": []}, {"text": "Australia", "isNumeric": false, "links": []}], [{"text": "56", "isNumeric": false, "links": []}, {"text": "Better People", "isNumeric": false, "links": ["http://www.wikipedia.org/wiki/Better_People"]}, {"text": "Xavier Rudd", "isNumeric": false, "links": ["http://www.wikipedia.org/wiki/Xavier_Rudd"]}, {"text": "Australia", "isNumeric": false, "links": []}], [{"text": "57", "isNumeric": false, "links": []}, {"text": "Into the Galaxy", "isNumeric": false, "links": []}, {"text": "Midnight Juggernauts", "isNumeric": false, "links": ["http://www.wikipedia.org/wiki/Midnight_Juggernauts"]}, {"text": "Australia", "isNumeric": false, "links": []}], [{"text": "58", "isNumeric": false, "links": []}, {"text": "Invincible", "isNumeric": false, "links": ["http://www.wikipedia.org/wiki/Invincible_(Muse_song)"]}, {"text": "Muse", "isNumeric": false, "links": []}, {"text": "United Kingdom", "isNumeric": false, "links": []}], [{"text": "59", "isNumeric": false, "links": []}, {"text": "Chelsea Dagger", "isNumeric": false, "links": ["http://www.wikipedia.org/wiki/Chelsea_Dagger"]}, {"text": "The Fratellis", "isNumeric": false, "links": ["http://www.wikipedia.org/wiki/The_Fratellis"]}, {"text": "United Kingdom", "isNumeric": false, "links": []}], [{"text": "60", "isNumeric": false, "links": []}, {"text": "Charmer", "isNumeric": false, "links": ["http://www.wikipedia.org/wiki/Charmer_(Kings_of_Leon_song)"]}, {"text": "Kings of Leon", "isNumeric": false, "links": []}, {"text": "United States", "isNumeric": false, "links": []}], [{"text": "61", "isNumeric": false, "links": []}, {"text": "Wayside", "isNumeric": false, "links": []}, {"text": "Birds of Tokyo", "isNumeric": false, "links": ["http://www.wikipedia.org/wiki/Birds_of_Tokyo"]}, {"text": "Australia", "isNumeric": false, "links": []}], [{"text": "62", "isNumeric": false, "links": []}, {"text": "No Longer There", "isNumeric": false, "links": ["http://www.wikipedia.org/wiki/No_Longer_There"]}, {"text": "The Cat Empire", "isNumeric": false, "links": []}, {"text": "Australia", "isNumeric": false, "links": []}], [{"text": "63", "isNumeric": false, "links": []}, {"text": "Gotye", "isNumeric": false, "links": ["http://www.wikipedia.org/wiki/Gotye"]}, {"text": "Karnivool", "isNumeric": false, "links": ["http://www.wikipedia.org/wiki/Karnivool"]}, {"text": "Australia", "isNumeric": false, "links": []}], [{"text": "64", "isNumeric": false, "links": []}, {"text": "Australia", "isNumeric": false, "links": ["http://www.wikipedia.org/wiki/Australia_(The_Shins_song)"]}, {"text": "The Shins", "isNumeric": false, "links": ["http://www.wikipedia.org/wiki/The_Shins"]}, {"text": "United States", "isNumeric": false, "links": []}], [{"text": "65", "isNumeric": false, "links": []}, {"text": "Smokers Outside the Hospital Doors", "isNumeric": false, "links": ["http://www.wikipedia.org/wiki/Smokers_Outside_the_Hospital_Doors"]}, {"text": "Editors", "isNumeric": false, "links": ["http://www.wikipedia.org/wiki/Editors_(band)"]}, {"text": "United Kingdom", "isNumeric": false, "links": []}], [{"text": "66", "isNumeric": false, "links": []}, {"text": "I Don't Remember", "isNumeric": false, "links": ["http://www.wikipedia.org/wiki/I_Don't_Remember"]}, {"text": "Powderfinger", "isNumeric": false, "links": []}, {"text": "Australia", "isNumeric": false, "links": []}], [{"text": "67", "isNumeric": false, "links": []}, {"text": "Rehab", "isNumeric": false, "links": ["http://www.wikipedia.org/wiki/Rehab_(Amy_Winehouse_song)"]}, {"text": "Amy Winehouse", "isNumeric": false, "links": ["http://www.wikipedia.org/wiki/Amy_Winehouse"]}, {"text": "United Kingdom", "isNumeric": false, "links": []}], [{"text": "68", "isNumeric": false, "links": []}, {"text": "Penny on the Train Track", "isNumeric": false, "links": []}, {"text": "Ben Kweller", "isNumeric": false, "links": ["http://www.wikipedia.org/wiki/Ben_Kweller"]}, {"text": "United States", "isNumeric": false, "links": []}], [{"text": "69", "isNumeric": false, "links": []}, {"text": "Pogo", "isNumeric": false, "links": []}, {"text": "Digitalism", "isNumeric": false, "links": ["http://www.wikipedia.org/wiki/Digitalism_(band)"]}, {"text": "Germany", "isNumeric": false, "links": ["http://www.wikipedia.org/wiki/Germany"]}], [{"text": "70", "isNumeric": false, "links": []}, {"text": "The Con", "isNumeric": false, "links": []}, {"text": "Tegan and Sara", "isNumeric": false, "links": []}, {"text": "Canada", "isNumeric": false, "links": []}], [{"text": "71", "isNumeric": false, "links": []}, {"text": "Reach", "isNumeric": false, "links": []}, {"text": "The Butterfly Effect", "isNumeric": false, "links": ["http://www.wikipedia.org/wiki/The_Butterfly_Effect_(band)"]}, {"text": "Australia", "isNumeric": false, "links": []}], [{"text": "72", "isNumeric": false, "links": []}, {"text": "Down the Line", "isNumeric": false, "links": ["http://www.wikipedia.org/wiki/In_Our_Nature"]}, {"text": "Jos\u00e9 Gonz\u00e1lez", "isNumeric": false, "links": ["http://www.wikipedia.org/wiki/Jos\u00e9_Gonz\u00e1lez"]}, {"text": "Sweden", "isNumeric": false, "links": ["http://www.wikipedia.org/wiki/Sweden"]}], [{"text": "73", "isNumeric": false, "links": []}, {"text": "Black Tattoo", "isNumeric": false, "links": ["http://www.wikipedia.org/wiki/Black_Tattoo"]}, {"text": "Grinspoon", "isNumeric": false, "links": ["http://www.wikipedia.org/wiki/Grinspoon"]}, {"text": "Australia", "isNumeric": false, "links": []}], [{"text": "74", "isNumeric": false, "links": []}, {"text": "Run the Red Light", "isNumeric": false, "links": ["http://www.wikipedia.org/wiki/Run_the_Red_Light"]}, {"text": "British India", "isNumeric": false, "links": []}, {"text": "Australia", "isNumeric": false, "links": []}], [{"text": "75", "isNumeric": false, "links": []}, {"text": "Shoot the Runner", "isNumeric": false, "links": ["http://www.wikipedia.org/wiki/Shoot_the_Runner"]}, {"text": "Kasabian", "isNumeric": false, "links": ["http://www.wikipedia.org/wiki/Kasabian"]}, {"text": "United Kingdom", "isNumeric": false, "links": []}], [{"text": "76", "isNumeric": false, "links": []}, {"text": "Sweaty", "isNumeric": false, "links": []}, {"text": "Muscles", "isNumeric": false, "links": []}, {"text": "Australia", "isNumeric": false, "links": []}], [{"text": "77", "isNumeric": false, "links": []}, {"text": "Get What You Want", "isNumeric": false, "links": ["http://www.wikipedia.org/wiki/Get_What_You_Want"]}, {"text": "Operator Please", "isNumeric": false, "links": []}, {"text": "Australia", "isNumeric": false, "links": []}], [{"text": "78", "isNumeric": false, "links": []}, {"text": "Brianstorm", "isNumeric": false, "links": ["http://www.wikipedia.org/wiki/Brianstorm"]}, {"text": "Arctic Monkeys", "isNumeric": false, "links": []}, {"text": "United Kingdom", "isNumeric": false, "links": []}], [{"text": "79", "isNumeric": false, "links": []}, {"text": "Lines On Palms", "isNumeric": false, "links": []}, {"text": "Josh Pyke", "isNumeric": false, "links": ["http://www.wikipedia.org/wiki/Josh_Pyke"]}, {"text": "Australia", "isNumeric": false, "links": []}], [{"text": "80", "isNumeric": false, "links": []}, {"text": "Reflections of a Sound", "isNumeric": false, "links": ["http://www.wikipedia.org/wiki/Reflections_of_a_Sound"]}, {"text": "Silverchair", "isNumeric": false, "links": []}, {"text": "Australia", "isNumeric": false, "links": []}], [{"text": "81", "isNumeric": false, "links": []}, {"text": "No Cars Go", "isNumeric": false, "links": ["http://www.wikipedia.org/wiki/No_Cars_Go"]}, {"text": "Arcade Fire", "isNumeric": false, "links": ["http://www.wikipedia.org/wiki/Arcade_Fire"]}, {"text": "Canada", "isNumeric": false, "links": []}], [{"text": "82", "isNumeric": false, "links": []}, {"text": "Long Road to Ruin", "isNumeric": false, "links": ["http://www.wikipedia.org/wiki/Long_Road_to_Ruin"]}, {"text": "Foo Fighters", "isNumeric": false, "links": []}, {"text": "United States", "isNumeric": false, "links": []}], [{"text": "83", "isNumeric": false, "links": []}, {"text": "Pleased to Meet You", "isNumeric": false, "links": []}, {"text": "Wolfmother", "isNumeric": false, "links": ["http://www.wikipedia.org/wiki/Wolfmother"]}, {"text": "Australia", "isNumeric": false, "links": []}], [{"text": "84", "isNumeric": false, "links": []}, {"text": "Do It Again", "isNumeric": false, "links": ["http://www.wikipedia.org/wiki/Do_It_Again_(The_Chemical_Brothers_song)"]}, {"text": "The Chemical Brothers", "isNumeric": false, "links": []}, {"text": "United Kingdom", "isNumeric": false, "links": []}], [{"text": "85", "isNumeric": false, "links": []}, {"text": "Down Boy", "isNumeric": false, "links": ["http://www.wikipedia.org/wiki/Is_Is"]}, {"text": "Yeah Yeah Yeahs", "isNumeric": false, "links": ["http://www.wikipedia.org/wiki/Yeah_Yeah_Yeahs"]}, {"text": "United States", "isNumeric": false, "links": []}], [{"text": "86", "isNumeric": false, "links": []}, {"text": "Tombstone", "isNumeric": false, "links": []}, {"text": "Midnight Juggernauts", "isNumeric": false, "links": []}, {"text": "Australia", "isNumeric": false, "links": []}], [{"text": "87", "isNumeric": false, "links": []}, {"text": "Eliza", "isNumeric": false, "links": []}, {"text": "Jackson Jackson", "isNumeric": false, "links": ["http://www.wikipedia.org/wiki/Jackson_Jackson"]}, {"text": "Australia", "isNumeric": false, "links": []}], [{"text": "88", "isNumeric": false, "links": []}, {"text": "The Message", "isNumeric": false, "links": []}, {"text": "The Cops", "isNumeric": false, "links": ["http://www.wikipedia.org/wiki/The_Cops_(Australian_band)"]}, {"text": "Australia", "isNumeric": false, "links": []}], [{"text": "89", "isNumeric": false, "links": []}, {"text": "Sick, Sick, Sick", "isNumeric": false, "links": ["http://www.wikipedia.org/wiki/Sick,_Sick,_Sick"]}, {"text": "Queens of the Stone Age", "isNumeric": false, "links": ["http://www.wikipedia.org/wiki/Queens_of_the_Stone_Age"]}, {"text": "United States", "isNumeric": false, "links": []}], [{"text": "90", "isNumeric": false, "links": []}, {"text": "When the Lights Went Down", "isNumeric": false, "links": []}, {"text": "Clare Bowditch and the Feeding Set", "isNumeric": false, "links": ["http://www.wikipedia.org/wiki/Clare_Bowditch"]}, {"text": "Australia", "isNumeric": false, "links": []}], [{"text": "91", "isNumeric": false, "links": []}, {"text": "Sew My Name", "isNumeric": false, "links": []}, {"text": "Josh Pyke", "isNumeric": false, "links": []}, {"text": "Australia", "isNumeric": false, "links": []}], [{"text": "92", "isNumeric": false, "links": []}, {"text": "Sun Dirt Water", "isNumeric": false, "links": ["http://www.wikipedia.org/wiki/Sun_Dirt_Water_(song)"]}, {"text": "The Waifs", "isNumeric": false, "links": ["http://www.wikipedia.org/wiki/The_Waifs"]}, {"text": "Australia", "isNumeric": false, "links": []}], [{"text": "93", "isNumeric": false, "links": []}, {"text": "Dr. Love", "isNumeric": false, "links": []}, {"text": "The Bumblebeez", "isNumeric": false, "links": ["http://www.wikipedia.org/wiki/The_Bumblebeez"]}, {"text": "Australia", "isNumeric": false, "links": []}], [{"text": "94", "isNumeric": false, "links": []}, {"text": "Jigsaw Falling Into Place", "isNumeric": false, "links": ["http://www.wikipedia.org/wiki/Jigsaw_Falling_into_Place"]}, {"text": "Radiohead", "isNumeric": false, "links": ["http://www.wikipedia.org/wiki/Radiohead"]}, {"text": "United Kingdom", "isNumeric": false, "links": []}], [{"text": "95", "isNumeric": false, "links": []}, {"text": "Samson", "isNumeric": false, "links": []}, {"text": "Regina Spektor", "isNumeric": false, "links": []}, {"text": "United States", "isNumeric": false, "links": []}], [{"text": "96", "isNumeric": false, "links": []}, {"text": "Love Me Like the World Is Ending", "isNumeric": false, "links": ["http://www.wikipedia.org/wiki/Love_Me_Like_the_World_Is_Ending"]}, {"text": "Ben Lee", "isNumeric": false, "links": ["http://www.wikipedia.org/wiki/Ben_Lee"]}, {"text": "Australia", "isNumeric": false, "links": []}], [{"text": "97", "isNumeric": false, "links": []}, {"text": "Forever Song", "isNumeric": false, "links": []}, {"text": "Josh Pyke", "isNumeric": false, "links": []}, {"text": "Australia", "isNumeric": false, "links": []}], [{"text": "98", "isNumeric": false, "links": []}, {"text": "The Heinrich Maneuver", "isNumeric": false, "links": ["http://www.wikipedia.org/wiki/The_Heinrich_Maneuver"]}, {"text": "Interpol", "isNumeric": false, "links": ["http://www.wikipedia.org/wiki/Interpol_(band)"]}, {"text": "United States", "isNumeric": false, "links": []}], [{"text": "99", "isNumeric": false, "links": []}, {"text": "Tick Tick Boom", "isNumeric": false, "links": ["http://www.wikipedia.org/wiki/Tick_Tick_Boom_(song)"]}, {"text": "The Hives", "isNumeric": false, "links": ["http://www.wikipedia.org/wiki/The_Hives"]}, {"text": "Sweden", "isNumeric": false, "links": []}], [{"text": "100", "isNumeric": false, "links": []}, {"text": "Wild Strawberries", "isNumeric": false, "links": []}, {"text": "Pnau", "isNumeric": false, "links": ["http://www.wikipedia.org/wiki/Pnau"]}, {"text": "Australia", "isNumeric": false, "links": []}]]}